purplship/mappers/dicom/__init__.py
purplship/mappers/dicom/mapper.py
purplship/mappers/dicom/proxy.py
purplship/mappers/dicom/settings.py
purplship/providers/dicom/__init__.py
purplship/providers/dicom/error.py
purplship/providers/dicom/pickup/__init__.py
purplship/providers/dicom/pickup/cancel.py
purplship/providers/dicom/pickup/create.py
purplship/providers/dicom/pickup/update.py
purplship/providers/dicom/rate.py
purplship/providers/dicom/shipment/__init__.py
purplship/providers/dicom/shipment/cancel.py
purplship/providers/dicom/shipment/create.py
purplship/providers/dicom/tracking.py
purplship/providers/dicom/units.py
purplship/providers/dicom/utils.py
purplship.dicom-2022.2.dist-info/WHEEL
purplship.dicom-2022.2.dist-info/METADATA
purplship.dicom-2022.2.dist-info/RECORD
